crypto_commons/__init__.py
crypto_commons/generic.py
crypto_commons/asymmetric/__init__.py
crypto_commons/asymmetric/asymmetric.py
crypto_commons/brute/__init__.py
crypto_commons/brute/brute.py
crypto_commons/netcat/__init__.py
crypto_commons/netcat/netcat_commons.py
crypto_commons/oracle/__init__.py
crypto_commons/oracle/lsb_oracle.py
crypto_commons/rsa/__init__.py
crypto_commons/rsa/crt.py
crypto_commons/rsa/rsa_commons.py
crypto_commons/symmetrical/__init__.py
crypto_commons/symmetrical/aes.py
crypto_commons/symmetrical/symmetrical.py
crypto_commons/xor/__init__.py
crypto_commons/xor/repeating_xor.py
crypto_commons-0.0.4.dist-info/METADATA
crypto_commons-0.0.4.dist-info/WHEEL
crypto_commons-0.0.4.dist-info/top_level.txt
crypto_commons-0.0.4.dist-info/RECORD
