Metadata-Version: 2.1
Name: crypto-commons
Version: 0.0.4
Summary: Small python module for common CTF crypto functions.
Home-page: https://github.com/p4-team/crypto-commons
Author: p4-team
Author-email: team@p4.team
License: UNKNOWN
Platform: UNKNOWN
Classifier: Programming Language :: Python :: 3
Classifier: License :: OSI Approved :: MIT License
Classifier: Operating System :: OS Independent
Requires-Dist: future ; python_version < "3.0"
